[
  {
    "strike": 400.0,
    "right": "C",
    "expiry": "20231229",
    "bid": 7.94,
    "ask": 10.0,
    "mid": 8.97,
    "volume": 45,
    "open_interest": 0
  },
  {
    "strike": 400.0,
    "right": "P",
    "expiry": "20231229",
    "bid": 0.01,
    "ask": 0.01,
    "mid": 0.01,
    "volume": 547,
    "open_interest": 0
  },
  {
    "strike": 405.0,
    "right": "C",
    "expiry": "20231229",
    "bid": 6.23,
    "ask": 4.03,
    "mid": 5.130000000000001,
    "volume": 423,
    "open_interest": 0
  },
  {
    "strike": 405.0,
    "right": "P",
    "expiry": "20231229",
    "bid": 0.05,
    "ask": 0.01,
    "mid": 0.030000000000000002,
    "volume": 8887,
    "open_interest": 0
  },
  {
    "strike": 410.0,
    "right": "C",
    "expiry": "20231229",
    "bid": 1.7,
    "ask": 0.03,
    "mid": 0.865,
    "volume": 65985,
    "open_interest": 0
  },
  {
    "strike": 410.0,
    "right": "P",
    "expiry": "20231229",
    "bid": 0.57,
    "ask": 0.7,
    "mid": 0.635,
    "volume": 46954,
    "open_interest": 0
  },
  {
    "strike": 415.0,
    "right": "C",
    "expiry": "20231229",
    "bid": 0.07,
    "ask": 0.01,
    "mid": 0.04,
    "volume": 18385,
    "open_interest": 0
  },
  {
    "strike": 415.0,
    "right": "P",
    "expiry": "20231229",
    "bid": 3.67,
    "ask": 5.83,
    "mid": 4.75,
    "volume": 272,
    "open_interest": 0
  },
  {
    "strike": 420.0,
    "right": "C",
    "expiry": "20231229",
    "bid": 0.01,
    "ask": 0.01,
    "mid": 0.01,
    "volume": 38,
    "open_interest": 0
  },
  {
    "strike": 420.0,
    "right": "P",
    "expiry": "20231229",
    "bid": 12.19,
    "ask": 12.26,
    "mid": 12.225,
    "volume": 2,
    "open_interest": 0
  }
]