[
  {
    "strike": 440.0,
    "right": "C",
    "expiry": "20241011",
    "bid": 51.01,
    "ask": 53.94,
    "mid": 52.474999999999994,
    "volume": 19,
    "open_interest": 0
  },
  {
    "strike": 440.0,
    "right": "P",
    "expiry": "20241011",
    "bid": 0.01,
    "ask": 0.01,
    "mid": 0.01,
    "volume": 51,
    "open_interest": 0
  },
  {
    "strike": 445.0,
    "right": "C",
    "expiry": "20241011",
    "bid": 48.2,
    "ask": 47.9,
    "mid": 48.05,
    "volume": 12,
    "open_interest": 0
  },
  {
    "strike": 445.0,
    "right": "P",
    "expiry": "20241011",
    "bid": 0.01,
    "ask": 0.01,
    "mid": 0.01,
    "volume": 16,
    "open_interest": 0
  },
  {
    "strike": 450.0,
    "right": "C",
    "expiry": "20241011",
    "bid": 40.24,
    "ask": 43.92,
    "mid": 42.08,
    "volume": 132,
    "open_interest": 0
  },
  {
    "strike": 450.0,
    "right": "P",
    "expiry": "20241011",
    "bid": 0.01,
    "ask": 0.01,
    "mid": 0.01,
    "volume": 84,
    "open_interest": 0
  },
  {
    "strike": 455.0,
    "right": "C",
    "expiry": "20241011",
    "bid": 35.9,
    "ask": 38.49,
    "mid": 37.195,
    "volume": 40,
    "open_interest": 0
  },
  {
    "strike": 455.0,
    "right": "P",
    "expiry": "20241011",
    "bid": 0.01,
    "ask": 0.01,
    "mid": 0.01,
    "volume": 177,
    "open_interest": 0
  },
  {
    "strike": 460.0,
    "right": "C",
    "expiry": "20241011",
    "bid": 30.56,
    "ask": 34.04,
    "mid": 32.3,
    "volume": 42,
    "open_interest": 0
  },
  {
    "strike": 460.0,
    "right": "P",
    "expiry": "20241011",
    "bid": 0.01,
    "ask": 0.01,
    "mid": 0.01,
    "volume": 187,
    "open_interest": 0
  },
  {
    "strike": 465.0,
    "right": "C",
    "expiry": "20241011",
    "bid": 26.43,
    "ask": 27.83,
    "mid": 27.13,
    "volume": 141,
    "open_interest": 0
  },
  {
    "strike": 465.0,
    "right": "P",
    "expiry": "20241011",
    "bid": 0.01,
    "ask": 0.01,
    "mid": 0.01,
    "volume": 24,
    "open_interest": 0
  },
  {
    "strike": 470.0,
    "right": "C",
    "expiry": "20241011",
    "bid": 20.57,
    "ask": 23.15,
    "mid": 21.86,
    "volume": 147,
    "open_interest": 0
  },
  {
    "strike": 470.0,
    "right": "P",
    "expiry": "20241011",
    "bid": 0.02,
    "ask": 0.01,
    "mid": 0.015,
    "volume": 2267,
    "open_interest": 0
  },
  {
    "strike": 475.0,
    "right": "C",
    "expiry": "20241011",
    "bid": 15.5,
    "ask": 18.87,
    "mid": 17.185000000000002,
    "volume": 243,
    "open_interest": 0
  },
  {
    "strike": 475.0,
    "right": "P",
    "expiry": "20241011",
    "bid": 0.02,
    "ask": 0.01,
    "mid": 0.015,
    "volume": 2013,
    "open_interest": 0
  },
  {
    "strike": 480.0,
    "right": "C",
    "expiry": "20241011",
    "bid": 10.61,
    "ask": 13.23,
    "mid": 11.92,
    "volume": 1470,
    "open_interest": 0
  },
  {
    "strike": 480.0,
    "right": "P",
    "expiry": "20241011",
    "bid": 0.06,
    "ask": 0.01,
    "mid": 0.034999999999999996,
    "volume": 5584,
    "open_interest": 0
  },
  {
    "strike": 485.0,
    "right": "C",
    "expiry": "20241011",
    "bid": 5.98,
    "ask": 7.86,
    "mid": 6.92,
    "volume": 4384,
    "open_interest": 0
  },
  {
    "strike": 485.0,
    "right": "P",
    "expiry": "20241011",
    "bid": 0.21,
    "ask": 0.01,
    "mid": 0.11,
    "volume": 14455,
    "open_interest": 0
  },
  {
    "strike": 490.0,
    "right": "C",
    "expiry": "20241011",
    "bid": 1.95,
    "ask": 2.89,
    "mid": 2.42,
    "volume": 27266,
    "open_interest": 0
  },
  {
    "strike": 490.0,
    "right": "P",
    "expiry": "20241011",
    "bid": 1.18,
    "ask": 0.01,
    "mid": 0.595,
    "volume": 106031,
    "open_interest": 0
  },
  {
    "strike": 495.0,
    "right": "C",
    "expiry": "20241011",
    "bid": 0.18,
    "ask": 0.01,
    "mid": 0.095,
    "volume": 114451,
    "open_interest": 0
  },
  {
    "strike": 495.0,
    "right": "P",
    "expiry": "20241011",
    "bid": 4.38,
    "ask": 2.12,
    "mid": 3.25,
    "volume": 16619,
    "open_interest": 0
  },
  {
    "strike": 500.0,
    "right": "C",
    "expiry": "20241011",
    "bid": 0.02,
    "ask": 0.01,
    "mid": 0.015,
    "volume": 7289,
    "open_interest": 0
  },
  {
    "strike": 500.0,
    "right": "P",
    "expiry": "20241011",
    "bid": 9.3,
    "ask": 6.26,
    "mid": 7.78,
    "volume": 399,
    "open_interest": 0
  },
  {
    "strike": 505.0,
    "right": "C",
    "expiry": "20241011",
    "bid": 0.01,
    "ask": 0.01,
    "mid": 0.01,
    "volume": 1002,
    "open_interest": 0
  },
  {
    "strike": 505.0,
    "right": "P",
    "expiry": "20241011",
    "bid": 14.43,
    "ask": 11.38,
    "mid": 12.905000000000001,
    "volume": 7,
    "open_interest": 0
  },
  {
    "strike": 510.0,
    "right": "C",
    "expiry": "20241011",
    "bid": 0.01,
    "ask": 0.01,
    "mid": 0.01,
    "volume": 55,
    "open_interest": 0
  },
  {
    "strike": 510.0,
    "right": "P",
    "expiry": "20241011",
    "bid": 19.47,
    "ask": 16.85,
    "mid": 18.16,
    "volume": 12,
    "open_interest": 0
  },
  {
    "strike": 515.0,
    "right": "C",
    "expiry": "20241011",
    "bid": 0.01,
    "ask": 0.01,
    "mid": 0.01,
    "volume": 343,
    "open_interest": 0
  },
  {
    "strike": 515.0,
    "right": "P",
    "expiry": "20241011",
    "bid": 22.79,
    "ask": 22.75,
    "mid": 22.77,
    "volume": 7,
    "open_interest": 0
  },
  {
    "strike": 520.0,
    "right": "C",
    "expiry": "20241011",
    "bid": 0.01,
    "ask": 0.01,
    "mid": 0.01,
    "volume": 21,
    "open_interest": 0
  },
  {
    "strike": 520.0,
    "right": "P",
    "expiry": "20241011",
    "bid": 28.5,
    "ask": 26.27,
    "mid": 27.384999999999998,
    "volume": 4,
    "open_interest": 0
  },
  {
    "strike": 530.0,
    "right": "C",
    "expiry": "20241011",
    "bid": 0.01,
    "ask": 0.01,
    "mid": 0.01,
    "volume": 1,
    "open_interest": 0
  },
  {
    "strike": 530.0,
    "right": "P",
    "expiry": "20241011",
    "bid": 39.26,
    "ask": 36.4,
    "mid": 37.83,
    "volume": 5,
    "open_interest": 0
  },
  {
    "strike": 540.0,
    "right": "C",
    "expiry": "20241011",
    "bid": 0.01,
    "ask": 0.01,
    "mid": 0.01,
    "volume": 3,
    "open_interest": 0
  }
]